LICENSE
MANIFEST.in
README.rst
setup.py
bin/autotest
pyautotest/__init__.py
pyautotest/cli.py
pyautotest/observers.py
pyautotest.egg-info/PKG-INFO
pyautotest.egg-info/SOURCES.txt
pyautotest.egg-info/dependency_links.txt
pyautotest.egg-info/requires.txt
pyautotest.egg-info/top_level.txt