Metadata-Version: 1.1
Name: pyautotest
Version: 0.1.0
Summary: Autotest Python unittest modules
Home-page: http://github.com/ascarter/pyautotest
Author: Andrew Carter
Author-email: andrew@ascarter.net
License: Copyright (c) 2013 Andrew Carter
